reladdons.py
reladdons-0.0.5.5.dist-info/WHEEL
reladdons-0.0.5.5.dist-info/METADATA
reladdons-0.0.5.5.dist-info/RECORD
