Metadata-Version: 2.1
Name: reladdons
Version: 0.0.5.5
Summary: the 4 version
Author: D1ffic00lt's Community
Author-email: dm.filinov@gmail.com
Requires-Python: >=3.7,<4.0
Classifier: Programming Language :: Python :: 3
Classifier: Programming Language :: Python :: 3.7
Classifier: Programming Language :: Python :: 3.8
Classifier: Programming Language :: Python :: 3.9
